spec_cli/__init__.py
spec_cli/cli.py
spec_cli-0.1.6.dist-info/METADATA
spec_cli-0.1.6.dist-info/WHEEL
spec_cli-0.1.6.dist-info/entry_points.txt
spec_cli-0.1.6.dist-info/RECORD
