Metadata-Version: 2.4
Name: spec-cli
Version: 0.1.6
Summary: AI 规则仓库自动配置工具，用于下载和配置 airules 的规则文件
Author: shirayner
Requires-Python: >=3.8
Requires-Dist: click>=8.0.0
